plastic_yellow_bird/__init__.py
plastic_yellow_bird/hello.py
plastic_yellow_bird-0.2.dev0.dist-info/LICENSE
plastic_yellow_bird-0.2.dev0.dist-info/METADATA
plastic_yellow_bird-0.2.dev0.dist-info/WHEEL
plastic_yellow_bird-0.2.dev0.dist-info/top_level.txt
plastic_yellow_bird-0.2.dev0.dist-info/RECORD
