Metadata-Version: 2.1
Name: plastic-yellow-bird
Version: 0.2.dev0
Summary: UNKNOWN
License: MIT
Platform: UNKNOWN
License-File: LICENSE
